netgraphix/__init__.py
netgraphix/core.py
netgraphix-0.1.0.dist-info/licenses/LICENSE
netgraphix-0.1.0.dist-info/METADATA
netgraphix-0.1.0.dist-info/WHEEL
netgraphix-0.1.0.dist-info/top_level.txt
netgraphix-0.1.0.dist-info/RECORD
