Metadata-Version: 2.4
Name: netgraphix
Version: 0.1.0
Summary: A real-time local network analyzer with live graphs and CLI features.
Home-page: https://github.com/EdenGithhub/netgraphix
Author: Adam Alcander et Eden
Author-email: Adam Alcander et Eden <aeden6877@gmail.com>
License: MIT
Project-URL: Homepage, https://github.com/EdenGithhub/netgraphix
Project-URL: Source, https://github.com/EdenGithhub/netgraphix
Project-URL: Issues, https://github.com/EdenGithhub/netgraphix/issues
Requires-Python: >=3.6
License-File: LICENSE
Requires-Dist: matplotlib
Requires-Dist: numpy
Requires-Dist: colorama
Requires-Dist: psutil
Requires-Dist: requests
Requires-Dist: tqdm
Requires-Dist: pyfiglet
Requires-Dist: scapy
Requires-Dist: rich
Requires-Dist: pandas
Requires-Dist: click
Requires-Dist: tabulate
Requires-Dist: py-cpuinfo
Dynamic: author
Dynamic: home-page
Dynamic: license-file
Dynamic: requires-python
